WFfiles/QNMData_a.txt
WFfiles/QNMData_fdamp.txt
WFfiles/QNMData_fring.txt
WFfiles/xiTide_Table_200.h5
gwfast/.patch/patch_ndt_complex_0-9-41.patch
gwfast/__init__.py
gwfast/fisherTools.py
gwfast/gwfastGlobals.py
gwfast/gwfastUtils.py
gwfast/network.py
gwfast/signal.py
gwfast/waveforms.py
psds/ET-0000A-18.txt
psds/ET_designs_comparison_paper/HFLF_cryo/ETLength10km.txt
psds/ET_designs_comparison_paper/HFLF_cryo/ETLength15km.txt
psds/ET_designs_comparison_paper/HFLF_cryo/ETLength20km.txt
psds/ET_designs_comparison_paper/HF_only/ETLength10km.txt
psds/ET_designs_comparison_paper/HF_only/ETLength15km.txt
psds/ET_designs_comparison_paper/HF_only/ETLength20km.txt
psds/LVC_O1O2O3/2017-06-10_DCH_C02_H1_O2_Sensitivity_strain_asd.txt
psds/LVC_O1O2O3/2017-08-06_DCH_C02_L1_O2_Sensitivity_strain_asd.txt
psds/LVC_O1O2O3/H1_asd-1262197260.txt
psds/LVC_O1O2O3/Hrec_hoft_V1O2Repro2A_16384Hz.txt
psds/LVC_O1O2O3/L1_asd-1262141640.txt
psds/LVC_O1O2O3/O3-H1-C01_CLEAN_SUB60HZ-1251752040.0_sensitivity_strain_asd.txt
psds/LVC_O1O2O3/O3-L1-C01_CLEAN_SUB60HZ-1240573680.0_sensitivity_strain_asd.txt
psds/LVC_O1O2O3/O3-V1_sensitivity_strain_asd.txt
psds/LVC_O1O2O3/V1_asd-1265246178.txt
psds/PSDs_README.md
psds/ce_strain/cosmic_explorer.txt
psds/ce_strain/cosmic_explorer_20km.txt
psds/ce_strain/cosmic_explorer_20km_pm.txt
psds/ce_strain/cosmic_explorer_40km_lf.txt
psds/observing_scenarios_paper/AplusDesign.txt
psds/observing_scenarios_paper/aligo_O3actual_H1.txt
psds/observing_scenarios_paper/aligo_O3actual_L1.txt
psds/observing_scenarios_paper/aligo_O4high.txt
psds/observing_scenarios_paper/aligo_O4low.txt
psds/observing_scenarios_paper/avirgo_O3actual.txt
psds/observing_scenarios_paper/avirgo_O4high_NEW.txt
psds/observing_scenarios_paper/avirgo_O5high_NEW.txt
psds/observing_scenarios_paper/avirgo_O5low_NEW.txt
psds/observing_scenarios_paper/kagra_10Mpc.txt
psds/observing_scenarios_paper/kagra_128Mpc.txt
psds/observing_scenarios_paper/kagra_25Mpc.txt
psds/observing_scenarios_paper/kagra_3Mpc.txt
gwfast-1.1.2.dist-info/LICENSE
gwfast-1.1.2.dist-info/METADATA
gwfast-1.1.2.dist-info/WHEEL
gwfast-1.1.2.dist-info/RECORD
