Metadata-Version: 2.1
Name: gwfast
Version: 1.1.2
Summary: A fisher matrix python package for GW studies
Home-page: https://github.com/CosmoStatGW/gwfast
License: GNU GPLv3
Keywords: python,automatic-differentiation,gravitational-waves,fisher-information,jax
Author: Francesco Iacovelli
Author-email: francesco.iacovelli@unige.ch
Maintainer: Niccolo' Muttoni
Maintainer-email: niccolo.muttoni@unige.ch
Requires-Python: >=3.9
Classifier: License :: Other/Proprietary License
Classifier: Programming Language :: Python :: 3
Classifier: Programming Language :: Python :: 3.9
Classifier: Programming Language :: Python :: 3.10
Classifier: Programming Language :: Python :: 3.11
Provides-Extra: docs
Provides-Extra: lal
Provides-Extra: teobresum
Requires-Dist: astropy (>=6.0.0,<6.1.0)
Requires-Dist: docutils (>=0.17.1,<0.18.0) ; extra == "docs"
Requires-Dist: h5py (>=3.2.1,<4.0.0)
Requires-Dist: jax[cpu] (>=0.4.26,<=0.4.30)
Requires-Dist: lalsuite ; extra == "lal"
Requires-Dist: mpmath (>=1.2.1,<2.0.0)
Requires-Dist: myst-parser (>=0.18.1,<0.19.0) ; extra == "docs"
Requires-Dist: nbsphinx (>=0.8.10) ; extra == "docs"
Requires-Dist: numdifftools (==0.9.41)
Requires-Dist: numpy (<=1.26.4)
Requires-Dist: readthedocs-sphinx-search (>=0.1.2,<0.2.0) ; extra == "docs"
Requires-Dist: schwimmbad (>=0.3.2,<0.4.0)
Requires-Dist: scipy (>=1.6.3)
Requires-Dist: sphinx (==5.3.0) ; extra == "docs"
Requires-Dist: sphinx-copybutton (>=0.5.1,<0.6.0) ; extra == "docs"
Requires-Dist: sphinx_rtd_theme (>=1.1.1) ; extra == "docs"
Requires-Dist: teobresums ; extra == "teobresum"
Project-URL: Documentation, https://gwfast.readthedocs.io/en/latest/
Project-URL: Repository, https://github.com/CosmoStatGW/gwfast
